linetools/__init__.py
linetools/io.py
linetools/line_utils.py
linetools/setup_package.py
linetools/spectralline.py
linetools/utils.py
linetools/version.py
linetools/abund/__init__.py
linetools/abund/elements.py
linetools/abund/ions.py
linetools/abund/relabund.py
linetools/abund/roman.py
linetools/abund/solar.py
linetools/abund/tests/__init__.py
linetools/abund/tests/test_elements.py
linetools/abund/tests/test_ions.py
linetools/abund/tests/test_relabnd.py
linetools/abund/tests/test_solar.py
linetools/analysis/__init__.py
linetools/analysis/abskin.py
linetools/analysis/absline.py
linetools/analysis/cog.py
linetools/analysis/continuum.py
linetools/analysis/continuumfnd.py
linetools/analysis/emline.py
linetools/analysis/interactive_plot.py
linetools/analysis/interp.py
linetools/analysis/plots.py
linetools/analysis/setup_package.py
linetools/analysis/utils.py
linetools/analysis/voigt.py
linetools/analysis/zlimits.py
linetools/analysis/tests/__init__.py
linetools/analysis/tests/test_abskin.py
linetools/analysis/tests/test_absline.py
linetools/analysis/tests/test_continuum.py
linetools/analysis/tests/test_continuumfnd.py
linetools/analysis/tests/test_interactive_plot.py
linetools/analysis/tests/test_interp.py
linetools/analysis/tests/test_io.py
linetools/analysis/tests/test_plots.py
linetools/analysis/tests/test_voigt.py
linetools/analysis/tests/test_zlimits.py
linetools/analysis/tests/files/spec1d_J0018p2345_KASTb_coadd.mod.out
linetools/data/abund/solar_Asplund2009.dat
linetools/data/atomic/verner96_photoion_table1.dat
linetools/data/lines/CO_UV.ascii
linetools/data/lines/EUV_lines.ascii
linetools/data/lines/Galaxy_linelist.ipynb
linetools/data/lines/H2_resonance.ascii
linetools/data/lines/ISM_table.fits
linetools/data/lines/cashman17.ascii
linetools/data/lines/galaxy_abs.ascii
linetools/data/lines/galaxy_forbidden.ascii
linetools/data/lines/galaxy_recomb.ascii
linetools/data/lines/howk00_table1.ascii
linetools/data/lines/linelist.ascii
linetools-0.3.1.dist-info/METADATA
linetools-0.3.1.dist-info/WHEEL
linetools-0.3.1.dist-info/entry_points.txt
linetools-0.3.1.dist-info/top_level.txt
linetools-0.3.1.dist-info/RECORD
