Metadata-Version: 2.1
Name: linetools
Version: 0.3.1
Summary: A package for analysing absorption and emission lines in 1d spectra, especially galaxy and quasar spectra.
Home-page: http://linetools.readthedocs.org/
Author: The linetools developers
Author-email: xavier@ucolick.org, neilcrighton@gmail.com
License: BSD-3
Keywords: linetools
Classifier: Development Status :: 4 - Beta
Classifier: Intended Audience :: Science/Research
Classifier: License :: OSI Approved :: BSD License
Classifier: Natural Language :: English
Classifier: Operating System :: OS Independent
Classifier: Programming Language :: Python
Classifier: Programming Language :: Python :: 3.8
Classifier: Programming Language :: Python :: 3.9
Classifier: Programming Language :: Python :: 3.10
Classifier: Topic :: Documentation :: Sphinx
Classifier: Topic :: Scientific/Engineering :: Astronomy
Classifier: Topic :: Software Development :: Libraries :: Python Modules
Classifier: Topic :: Software Development :: User Interfaces
Requires-Python: >=3.8
Requires-Dist: numpy (>=1.20)
Requires-Dist: astropy (>=5.2.1)
Requires-Dist: scipy (>=1.6)
Requires-Dist: h5py (>=3.7)
Requires-Dist: matplotlib (>=3.3)
Requires-Dist: PyYAML (>=5.1)
Requires-Dist: IPython (>=7.10.0)
Requires-Dist: qtpy (>=1.9)
Provides-Extra: dev
Requires-Dist: pytest (>=6.0.0) ; extra == 'dev'
Requires-Dist: pytest-astropy ; extra == 'dev'
Requires-Dist: tox ; extra == 'dev'
Requires-Dist: pytest-cov ; extra == 'dev'
Requires-Dist: coverage ; extra == 'dev'
Requires-Dist: codecov ; extra == 'dev'
Requires-Dist: sphinx ; extra == 'dev'
Requires-Dist: sphinx-automodapi ; extra == 'dev'
Requires-Dist: sphinx-rtd-theme ; extra == 'dev'
Provides-Extra: docs
Requires-Dist: sphinx ; extra == 'docs'
Requires-Dist: sphinx-automodapi ; extra == 'docs'
Requires-Dist: sphinx-rtd-theme ; extra == 'docs'
Provides-Extra: pyqt5
Requires-Dist: pyqt5 ; extra == 'pyqt5'
Provides-Extra: pyside2
Requires-Dist: pyside2 (>=5.0) ; extra == 'pyside2'
Provides-Extra: test
Requires-Dist: pytest (>=6.0.0) ; extra == 'test'
Requires-Dist: pytest-astropy ; extra == 'test'
Requires-Dist: tox ; extra == 'test'
Requires-Dist: pytest-cov ; extra == 'test'
Requires-Dist: coverage ; extra == 'test'
Requires-Dist: codecov ; extra == 'test'
